odoo10_addon_account_invoice_line_report-10.0.1.0.0-py2.7-nspkg.pth
odoo/addons/account_invoice_line_report/README.rst
odoo/addons/account_invoice_line_report/__init__.py
odoo/addons/account_invoice_line_report/__manifest__.py
odoo/addons/account_invoice_line_report/i18n/ar.po
odoo/addons/account_invoice_line_report/i18n/bs.po
odoo/addons/account_invoice_line_report/i18n/ca.po
odoo/addons/account_invoice_line_report/i18n/cs.po
odoo/addons/account_invoice_line_report/i18n/de.po
odoo/addons/account_invoice_line_report/i18n/en_GB.po
odoo/addons/account_invoice_line_report/i18n/es.po
odoo/addons/account_invoice_line_report/i18n/es_CR.po
odoo/addons/account_invoice_line_report/i18n/es_EC.po
odoo/addons/account_invoice_line_report/i18n/es_MX.po
odoo/addons/account_invoice_line_report/i18n/et.po
odoo/addons/account_invoice_line_report/i18n/fr.po
odoo/addons/account_invoice_line_report/i18n/fr_CH.po
odoo/addons/account_invoice_line_report/i18n/hr.po
odoo/addons/account_invoice_line_report/i18n/hr_HR.po
odoo/addons/account_invoice_line_report/i18n/hu.po
odoo/addons/account_invoice_line_report/i18n/it.po
odoo/addons/account_invoice_line_report/i18n/ja.po
odoo/addons/account_invoice_line_report/i18n/lt.po
odoo/addons/account_invoice_line_report/i18n/mk.po
odoo/addons/account_invoice_line_report/i18n/mn.po
odoo/addons/account_invoice_line_report/i18n/nb.po
odoo/addons/account_invoice_line_report/i18n/nl.po
odoo/addons/account_invoice_line_report/i18n/nl_BE.po
odoo/addons/account_invoice_line_report/i18n/nl_NL.po
odoo/addons/account_invoice_line_report/i18n/pt.po
odoo/addons/account_invoice_line_report/i18n/pt_BR.po
odoo/addons/account_invoice_line_report/i18n/pt_PT.po
odoo/addons/account_invoice_line_report/i18n/ro.po
odoo/addons/account_invoice_line_report/i18n/ru.po
odoo/addons/account_invoice_line_report/i18n/sl.po
odoo/addons/account_invoice_line_report/i18n/sv.po
odoo/addons/account_invoice_line_report/i18n/tr.po
odoo10_addon_account_invoice_line_report-10.0.1.0.0.dist-info/DESCRIPTION.rst
odoo10_addon_account_invoice_line_report-10.0.1.0.0.dist-info/METADATA
odoo10_addon_account_invoice_line_report-10.0.1.0.0.dist-info/RECORD
odoo10_addon_account_invoice_line_report-10.0.1.0.0.dist-info/WHEEL
odoo10_addon_account_invoice_line_report-10.0.1.0.0.dist-info/metadata.json
odoo10_addon_account_invoice_line_report-10.0.1.0.0.dist-info/namespace_packages.txt
odoo10_addon_account_invoice_line_report-10.0.1.0.0.dist-info/top_level.txt
